{"date":"1980-01-07","platform":"TV","images":{"small":"https://lain.bgm.tv/r/200/pic/cover/l/bf/77/213645_6WIsw.jpg","grid":"https://lain.bgm.tv/r/100/pic/cover/l/bf/77/213645_6WIsw.jpg","large":"https://lain.bgm.tv/pic/cover/l/bf/77/213645_6WIsw.jpg","medium":"https://lain.bgm.tv/r/800/pic/cover/l/bf/77/213645_6WIsw.jpg","common":"https://lain.bgm.tv/r/400/pic/cover/l/bf/77/213645_6WIsw.jpg"},"summary":"　タツノコプロが東急エージェンシーと連携して製作した、オリジナルのメルヘンTVアニメ。\r\n　森の中には、陽気な小人ファニット族が住んでいた。温厚で働き者の彼らだが、中でも男子のリルビット、女子のベルフィーは子供たちの人気者だ。孤児のベルフィーは、保護者の医師ドックリンと共同生活。ベルフィーの方が、お酒好きの先生のお母さん的な立場になることもある。リルビットは両親と妹との4人家族。だが父のロックが仲間にまじって働かず、一心にトンネルを掘り続けることが気がかりだった。とはいえベルフィーとリルビットも、普段は森の小さな探検隊。村長の息子ナポレオンたちを仲間に、今日も冒険を始めるのだった。監督は、スタジオぴえろ作品でも活躍の林政行。本作の美術はロウを溶かして塗るなど、特殊効果も試みた。そのおかげで独特の雰囲気があるものになっている。","name":"森の陽気な小人たち ベルフィーとリルビット","name_cn":"森林里的快乐小精灵们 Belfy与Lillibit","tags":[{"name":"1980","count":1,"total_cont":0},{"name":"龙之子","count":1,"total_cont":0},{"name":"日本","count":1,"total_cont":0},{"name":"TV","count":1,"total_cont":0}],"infobox":[{"key":"中文名","value":"森林里的快乐小精灵们 Belfy与Lillibit"},{"key":"别名","value":[{"v":"小可愛"}]},{"key":"话数","value":"26"},{"key":"放送开始","value":"1980年1月7日"},{"key":"放送星期","value":"星期一"},{"key":"播放结束","value":"1980年6月30日"}],"rating":{"rank":0,"total":0,"count":{"1":0,"2":0,"3":0,"4":0,"5":0,"6":0,"7":0,"8":0,"9":0,"10":0},"score":0},"total_episodes":26,"collection":{"on_hold":1,"dropped":4,"wish":6,"collect":1,"doing":2},"id":213645,"eps":26,"meta_tags":["TV","日本","原创"],"volumes":0,"series":false,"locked":false,"nsfw":false,"type":2}