{"date":"2002-12-31","platform":"TV","images":{"small":"https://lain.bgm.tv/r/200/pic/cover/l/90/af/112448_4EXXk.jpg","grid":"https://lain.bgm.tv/r/100/pic/cover/l/90/af/112448_4EXXk.jpg","large":"https://lain.bgm.tv/pic/cover/l/90/af/112448_4EXXk.jpg","medium":"https://lain.bgm.tv/r/800/pic/cover/l/90/af/112448_4EXXk.jpg","common":"https://lain.bgm.tv/r/400/pic/cover/l/90/af/112448_4EXXk.jpg"},"summary":"　　生活在垃圾堆生活的阿渍（Mr. Stain）是一个流浪汉，在被丢满垃圾的后巷发现垃圾，会当做未发现的宝物。他们的生活片段古灵精怪、荒唐又充满笑料，但细心回味之下，就会发觉笑中有泪。导演的目的就是让观众在轻松之后来点反思，娱乐得来也有得益。 ","name":"ガラクタ通りのステイン","name_cn":"阿渍的垃圾堆","tags":[{"name":"TV","count":3,"total_cont":0},{"name":"2002","count":3,"total_cont":0},{"name":"増田龍治","count":2,"total_cont":0},{"name":"动画","count":1,"total_cont":0},{"name":"Funimation","count":1,"total_cont":0},{"name":"日本","count":1,"total_cont":0},{"name":"空","count":1,"total_cont":0},{"name":"t","count":1,"total_cont":0}],"infobox":[{"key":"中文名","value":"阿渍的垃圾堆"},{"key":"别名","value":[{"v":"Ga-Ra-Ku-Ta: Mr. Stain on Junk Alley"}]},{"key":"话数","value":"14"},{"key":"放送开始","value":"2002年12月31日"},{"key":"放送星期","value":"星期二"},{"key":"导演","value":"増田龍治"}],"rating":{"rank":0,"total":2,"count":{"1":0,"2":0,"3":0,"4":0,"5":0,"6":2,"7":0,"8":0,"9":0,"10":0},"score":6},"total_episodes":14,"collection":{"on_hold":4,"dropped":6,"wish":10,"collect":8,"doing":0},"id":112448,"eps":14,"meta_tags":["TV","日本"],"volumes":0,"series":false,"locked":false,"nsfw":false,"type":2}