{"date":"2025-10-11","platform":"TV","images":{"small":"https://lain.bgm.tv/r/200/pic/cover/l/17/82/526448_ssr71.jpg","grid":"https://lain.bgm.tv/r/100/pic/cover/l/17/82/526448_ssr71.jpg","large":"https://lain.bgm.tv/pic/cover/l/17/82/526448_ssr71.jpg","medium":"https://lain.bgm.tv/r/800/pic/cover/l/17/82/526448_ssr71.jpg","common":"https://lain.bgm.tv/r/400/pic/cover/l/17/82/526448_ssr71.jpg"},"summary":"故事发生在一艘漂流的太空船上。由于一种“会伪装成人类来袭击人类的未知敌人”——「古诺希亚」混入船内，互相猜疑的乘员们决定每天投票选出一名可疑人物，让其进入冷冻睡眠。\r\n如果能让所有古诺希亚全部进入冷冻睡眠则人类获胜。反之，若无法找出古诺希亚，乘员们就会遭到袭击。主人公尤里必须要做出正确的选择，与此同时，他发现自己陷入了一个时间循环中，无论做出怎样的选择，都会回到第一天。\r\n乘员们究竟能否做出正确的选择？时间循环背后隐藏的秘密是什么？随着故事发展，乘员们不为人知的真面目也逐渐浮出水面。\r\n在短暂的时间里不断重复，一瞬却仿佛永恒的故事，如今拉开帷幕。\r\n——那么，祝您旅途愉快。\r\n\r\n\r\n[简介原文]\r\n物語の舞台は漂流する宇宙船。“人間に化けて人間を襲う未知の敵”一「グノーシア」が船内に紛れこんだことを受けて、乗員たちは疑心暗鬼の中、毎日1人ずつ疑わしい者を投票で選び、コールドスリープさせることを決める。\r\nグノーシアを全てコールドスリープさせることができれば人間の勝利。逆にグノーシアを当てられなければ、乗員たちは襲われてしまう。正しい選択が求められる中、なんと主人公・ユーリは、どのような選択をしても、最初の1日目にループする事態に。\r\nはたして乗員たちは正しい選択をすることができるのか？タイムリープに隠された秘密とは？そして明らかになる、乗員たちの隠された素顔とは——？\r\nわずかな時間を繰りかえす、一瞬にして永遠のような物語が、いま、幕を開ける。\r\n——それでは、良い旅を。","name":"グノーシア","name_cn":"古诺希亚","tags":[{"name":"游戏改","count":1305,"total_cont":0},{"name":"悬疑","count":1183,"total_cont":0},{"name":"2025年10月","count":1094,"total_cont":0},{"name":"科幻","count":975,"total_cont":0},{"name":"花田十辉","count":780,"total_cont":0},{"name":"轮回","count":697,"total_cont":0},{"name":"TV","count":675,"total_cont":0},{"name":"domerica","count":467,"total_cont":0},{"name":"2025","count":387,"total_cont":0},{"name":"日本","count":347,"total_cont":0},{"name":"推理","count":280,"total_cont":0},{"name":"Aniplex","count":247,"total_cont":0},{"name":"SF","count":118,"total_cont":0},{"name":"市川量也","count":106,"total_cont":0},{"name":"2025年","count":97,"total_cont":0},{"name":"狼人杀","count":43,"total_cont":0},{"name":"藤村鼓乃美","count":23,"total_cont":0},{"name":"智斗","count":22,"total_cont":0},{"name":"早见沙织","count":13,"total_cont":0},{"name":"2026年1月","count":12,"total_cont":0},{"name":"佐仓绫音","count":11,"total_cont":0},{"name":"花泽香菜","count":11,"total_cont":0},{"name":"安济知佳","count":10,"total_cont":0},{"name":"鬼头明里","count":10,"total_cont":0},{"name":"津田健次郎","count":10,"total_cont":0},{"name":"长谷川育美","count":10,"total_cont":0},{"name":"花田十輝","count":9,"total_cont":0},{"name":"关智一","count":9,"total_cont":0},{"name":"大冢刚央","count":8,"total_cont":0},{"name":"游戏改编","count":7,"total_cont":0}],"infobox":[{"key":"中文名","value":"古诺希亚"},{"key":"别名","value":[{"v":"宇宙人狼"},{"v":"GNOSIA"}]},{"key":"话数","value":"21"},{"key":"放送开始","value":"2025年10月11日"},{"key":"放送星期","value":"星期六"},{"key":"官方网站","value":"https://gnosia-anime.com/"},{"key":"播放电视台","value":"TOKYO MX / BS11 / とちぎテレビ / 群馬テレビ"},{"key":"其他电视台","value":"テレビ愛知 / MBS"},{"key":"导演","value":"市川量也"},{"key":"音乐","value":"深澤秀行"},{"key":"Copyright","value":"©Petit Depotto/Project D.Q.O."},{"key":"原作","value":"プチデポット"},{"key":"人物设定","value":"松浦有紗"},{"key":"人狼监修","value":"松崎史也"},{"key":"人物原案","value":"ことり"},{"key":"主题歌演出","value":"MAISONdes feat. こぼ・かなえる, 重音テト, Giga(ギガP) & TeddyLoid / 凛として時雨"},{"key":"製作","value":"Project D.Q.O.【Aniplex（三宅将典、清水博之、高橋祐馬、鳥羽洋典、淀明子、足立和紀、清水広美、君島裕喜、岡田武士、谷池侑美、松﨑由美子）、ドメリカ、TOKYO MX（買場道雄、照井健、橋本京佳）、日本BS放送（大和田智之、東真央）、ムービック（外川明宏、三浦史）、PLAYISM（水谷俊次）、プチデポット（めづかれ、しごと、ことり、Q flavor）】"},{"key":"企画","value":"岩上敦宏、市川量也、佐藤真紀、羽川寛、髙橋竜、川勝徹"},{"key":"制片人","value":"川勝徹、木村吉隆"},{"key":"助理制片人","value":"高須秋、西田文哉"},{"key":"企画协力","value":"佐藤茂薫、月岡佑紀、佐藤顕、石橋杏果"},{"key":"录音","value":"岡部直紀"},{"key":"录音工作室","value":"スタジオマウス"},{"key":"录音助理","value":"藤澤卓"},{"key":"音响","value":"スタジオマウス；音响制作担当：石黒尚人"},{"key":"音乐制作人","value":"山内真治"},{"key":"音乐监督","value":"安谷屋光生"},{"key":"音乐制作","value":"Aniplex；音乐制作协力：ミラクル・バス"},{"key":"CG 导演","value":"鎌田麻友美、飯田祐輝"},{"key":"2D 设计","value":"大橋治紀、野口毬愛、大川竜之介、野津摩璃乃、谷口初音、藤田真以子"}],"rating":{"rank":782,"total":2473,"count":{"1":10,"2":4,"3":6,"4":25,"5":54,"6":150,"7":745,"8":1200,"9":208,"10":71},"score":7.6},"total_episodes":21,"collection":{"on_hold":244,"dropped":175,"wish":3067,"collect":750,"doing":8292},"id":526448,"eps":21,"meta_tags":["科幻","悬疑","TV","日本","游戏改"],"volumes":0,"series":false,"locked":false,"nsfw":false,"type":2}