{"date":"2025-12-25","platform":"TV","images":{"small":"https://lain.bgm.tv/r/200/pic/cover/l/fc/b5/506120_1gOlU.jpg","grid":"https://lain.bgm.tv/r/100/pic/cover/l/fc/b5/506120_1gOlU.jpg","large":"https://lain.bgm.tv/pic/cover/l/fc/b5/506120_1gOlU.jpg","medium":"https://lain.bgm.tv/r/800/pic/cover/l/fc/b5/506120_1gOlU.jpg","common":"https://lain.bgm.tv/r/400/pic/cover/l/fc/b5/506120_1gOlU.jpg"},"summary":"　ユニオンを裏切り、円卓を手にしたビリー。UMAウィンターによる吹雪の中、オータム戦の報告を受け、不死と不運が進化していることを知る。そこにジュイスが現れ、古代遺物は神を倒すための武器であること、アークがあと1回のループしかできないことを明かし、共通の目的である“神を倒す”ために共に戦い不運に賭けようと説得を試みる。だがビリーは「俺達は組めない」と言い放つのだった。してアークとアポカリプスを手に入れようと画策していたビリーの思惑に気づくジュイスだが、UMAも入り乱れての激闘が始まってしまう。互いの正義に覚悟を決め、苛烈に迫るジュイスの剣に、他の否定者の能力と銃で対するビリー。ビリーが真に欲するものは何なのか——一方、オータムのコアを捕獲したアンディと風子は、空路でサマー討伐に向かっていた。だが、ジュイスがアポカリプスをアンディに託していたことがビリーに読まれ、放たれた刺客が空中から二人に襲い来る！\r\n","name":"アンデッドアンラック Winter編","name_cn":"不死不幸 冬季篇","tags":[{"name":"漫画改","count":88,"total_cont":0},{"name":"战斗","count":87,"total_cont":0},{"name":"2025","count":85,"total_cont":0},{"name":"TV","count":69,"total_cont":0},{"name":"奇幻","count":65,"total_cont":0},{"name":"热血","count":55,"total_cont":0},{"name":"2025年1月","count":52,"total_cont":0},{"name":"davidproduction","count":50,"total_cont":0},{"name":"漫改","count":42,"total_cont":0},{"name":"不死不幸","count":39,"total_cont":0},{"name":"E&Hproduction","count":32,"total_cont":0},{"name":"日本","count":32,"total_cont":0},{"name":"朴性厚","count":26,"total_cont":0},{"name":"续作","count":22,"total_cont":0},{"name":"TVSP","count":12,"total_cont":0},{"name":"2025年10月","count":11,"total_cont":0},{"name":"2025年12月","count":11,"total_cont":0},{"name":"OVA","count":10,"total_cont":0},{"name":"剧场版","count":9,"total_cont":0},{"name":"Production","count":4,"total_cont":0},{"name":"2026年1月","count":4,"total_cont":0},{"name":"E&H","count":4,"total_cont":0},{"name":"恋爱","count":3,"total_cont":0},{"name":"八瀬祐樹","count":3,"total_cont":0},{"name":"中村悠一","count":2,"total_cont":0},{"name":"OAD","count":2,"total_cont":0},{"name":"2026","count":2,"total_cont":0},{"name":"超能力","count":2,"total_cont":0},{"name":"番外","count":1,"total_cont":0},{"name":"动画","count":1,"total_cont":0}],"infobox":[{"key":"中文名","value":"不死不幸 冬季篇"},{"key":"别名","value":[{"v":"アンデッドアンラック ウィンター編"}]},{"key":"话数","value":"1"},{"key":"放送开始","value":"2025年12月25日"},{"key":"放送星期","value":"星期四"},{"key":"官方网站","value":"https://undead-unluck.net/"},{"key":"播放电视台","value":"MBS・TBS系"},{"key":"导演","value":"朴性厚"},{"key":"Copyright","value":"©戸塚慶文／集英社・アンデッドアンラック製作委員会"},{"key":"原作","value":"戸塚慶文（集英社 ジャンプコミックス刊）"},{"key":"人物设定","value":"守岡英行、石本峻一"},{"key":"设定","value":"三輪和宏"},{"key":"协力","value":"開発協力：david production"}],"rating":{"rank":6951,"total":263,"count":{"1":1,"2":2,"3":3,"4":17,"5":35,"6":123,"7":71,"8":10,"9":0,"10":1},"score":6},"total_episodes":1,"collection":{"on_hold":34,"dropped":18,"wish":494,"collect":397,"doing":154},"id":506120,"eps":1,"meta_tags":["TV","日本","奇幻","漫画改","战斗"],"volumes":0,"series":false,"locked":false,"nsfw":false,"type":2}