{"date":"2025-07-12","platform":"TV","images":{"small":"https://lain.bgm.tv/r/200/pic/cover/l/dd/5d/564314_DfcHG.jpg","grid":"https://lain.bgm.tv/r/100/pic/cover/l/dd/5d/564314_DfcHG.jpg","large":"https://lain.bgm.tv/pic/cover/l/dd/5d/564314_DfcHG.jpg","medium":"https://lain.bgm.tv/r/800/pic/cover/l/dd/5d/564314_DfcHG.jpg","common":"https://lain.bgm.tv/r/400/pic/cover/l/dd/5d/564314_DfcHG.jpg"},"summary":"スマホで5分、 この体験は、物語の新たなる挑戦だ。作家たちの出会いが、これまでにない手法が、新しい物語を創り出す。新感覚ショートアニメ『ラノベアニメ』始まる。\r\n■傷心タイムリープ\r\n■ファムファタル育成計画\r\n■Jack the Reaper\r\n■マリー・アントワネットに転生したので全力でギロチンを回避します\r\nYouTubeにて6月12日配信スタート。\r\n2025年7月13日(日)ABCテレビ・テレビ朝日系列全国24局ネット『ANiMAZiNG!!!』枠にて02:00～放送開始\r\nABCアニメ・朝日系列の「ANiMAZiNG!!!（アニメイジング）」枠にて、下記4作品をTVアニメ用に横型画面で再編集した同4作品を『週刊ラノベアニメ』として放送決定！!\r\n\r\n本片包含『Jack the Reaper』、『傷心タイムリープ』、『ファムファタル育成計画』、『マリー・アントワネットに転生したので全力でギロチンを回避します』4个故事，每周更新整合后的一集（4作品各5分钟），以『週刊ラノべアニメ』为番组名播出。","name":"週刊ラノべアニメ","name_cn":"","tags":[{"name":"2025","count":7,"total_cont":0},{"name":"TV","count":4,"total_cont":0},{"name":"WEB","count":4,"total_cont":0},{"name":"短片","count":4,"total_cont":0},{"name":"原创","count":3,"total_cont":0},{"name":"2025年7月","count":2,"total_cont":0},{"name":"日本","count":2,"total_cont":0},{"name":"TVA","count":1,"total_cont":0}],"infobox":[{"key":"别名","value":[{"v":"ラノアニ"}]},{"key":"话数","value":"12"},{"key":"放送开始","value":"2025年7月12日"},{"key":"放送星期","value":"星期六"},{"key":"官方网站","value":"https://lightnovel-anime.com/"},{"key":"在线播放平台","value":"YOUTUBE（先行放送）"},{"key":"播放电视台","value":"ABCテレビ・テレビ朝日"},{"key":"其他电视台","value":"HTB北海道テレビ、メ～テレ"},{"key":"播放结束","value":"2025年9月27日"},{"key":"Copyright","value":"©ラノベアニメ製作委員会"}],"rating":{"rank":0,"total":10,"count":{"1":3,"2":3,"3":0,"4":0,"5":3,"6":0,"7":1,"8":0,"9":0,"10":0},"score":3.1},"total_episodes":12,"collection":{"on_hold":2,"dropped":18,"wish":22,"collect":9,"doing":4},"id":564314,"eps":12,"meta_tags":["TV","日本","原创"],"volumes":0,"series":false,"locked":false,"nsfw":false,"type":2}