{"date":"2026-01-08","platform":"WEB","images":{"small":"https://lain.bgm.tv/r/200/pic/cover/l/0c/21/620404_Wgphc.jpg","grid":"https://lain.bgm.tv/r/100/pic/cover/l/0c/21/620404_Wgphc.jpg","large":"https://lain.bgm.tv/pic/cover/l/0c/21/620404_Wgphc.jpg","medium":"https://lain.bgm.tv/r/800/pic/cover/l/0c/21/620404_Wgphc.jpg","common":"https://lain.bgm.tv/r/400/pic/cover/l/0c/21/620404_Wgphc.jpg"},"summary":"無免許の天才外科医として知られるブラック・ジャックが、そろ谷版スピンオフでは、破天荒すぎる残念キャラとして登場。クールに決めた直後にボロを出したり、感動の場面を台無しにしたりと、予想を裏切るズレた言動を連発します。\r\n\r\nそこに助手のピノコが関西弁で鋭くのツッコミを入れることでテンポのよいコントアニメを展開します。毎話さまざまな悩みを抱えた患者たちが登場しては、ブラック・ジャックに治療を依頼する全12話構成のショートアニメです。","name":"ブラックジャックやねん","name_cn":"","tags":[{"name":"WEB","count":1,"total_cont":0},{"name":"漫画改","count":1,"total_cont":0},{"name":"日本","count":1,"total_cont":0}],"infobox":[{"key":"话数","value":"12"},{"key":"放送开始","value":"2026年1月8日"},{"key":"放送星期","value":"星期四"},{"key":"官方网站","value":"https://www.sukiani.jp/"},{"key":"在线播放平台","value":"YouTube"},{"key":"导演","value":"そろ谷"},{"key":"Copyright","value":"©Tezuka Productions/DLE,KDDI"},{"key":"原作","value":"手塚治虫『ブラック・ジャック』"},{"key":"脚本","value":"そろ谷"},{"key":"演出","value":"野中勇希"},{"key":"动画制作","value":"DLE"},{"key":"制作协力","value":"手塚プロダクション"}],"rating":{"rank":0,"total":0,"count":{"1":0,"2":0,"3":0,"4":0,"5":0,"6":0,"7":0,"8":0,"9":0,"10":0},"score":0},"total_episodes":12,"collection":{"on_hold":0,"dropped":1,"wish":0,"collect":0,"doing":2},"id":620404,"eps":12,"meta_tags":["日本","漫画改","WEB"],"volumes":0,"series":false,"locked":false,"nsfw":false,"type":2}