{"date":"2024-11-21","platform":"WEB","images":{"small":"https://lain.bgm.tv/r/200/pic/cover/l/0a/2c/497924_r8t1p.jpg","grid":"https://lain.bgm.tv/r/100/pic/cover/l/0a/2c/497924_r8t1p.jpg","large":"https://lain.bgm.tv/pic/cover/l/0a/2c/497924_r8t1p.jpg","medium":"https://lain.bgm.tv/r/800/pic/cover/l/0a/2c/497924_r8t1p.jpg","common":"https://lain.bgm.tv/r/400/pic/cover/l/0a/2c/497924_r8t1p.jpg"},"summary":"「Tokyo Override」はAIが暮らしに溶け込み、都市生活のすべてが自動化された100年後の東京が舞台。表向きは“理想的な社会”であるはずの街に潜む巨悪の存在を、はみ出しものの主人公たちが暴いていくバイクアクションSFアニメ","name":"Tokyo Override","name_cn":"东京暗递","tags":[{"name":"WEB","count":6,"total_cont":0},{"name":"2024","count":5,"total_cont":0},{"name":"RiFFStudio","count":5,"total_cont":0},{"name":"原创","count":4,"total_cont":0},{"name":"科幻","count":3,"total_cont":0},{"name":"2024年10月","count":3,"total_cont":0},{"name":"日本动画","count":2,"total_cont":0},{"name":"ファイルーズあい","count":2,"total_cont":0},{"name":"SF","count":2,"total_cont":0},{"name":"日本","count":2,"total_cont":0},{"name":"深田祐辅","count":1,"total_cont":0},{"name":"竹内良太","count":1,"total_cont":0},{"name":"深田祐輔","count":1,"total_cont":0},{"name":"ヴィーラパトラ・ジナナヴィン","count":1,"total_cont":0},{"name":"TV","count":1,"total_cont":0}],"infobox":[{"key":"中文名","value":"东京暗递"},{"key":"话数","value":"6"},{"key":"放送开始","value":"2024年11月21日"},{"key":"官方网站","value":"https://global.yamaha-motor.com/jp/showroom/tokyooverride/"},{"key":"在线播放平台","value":"Netflix"},{"key":"播放结束","value":"2024年11月21日"},{"key":"导演","value":"深田祐輔、Veerapatra Jinanavin"},{"key":"协力","value":"本田技研工業株式会社、ヤマハ発動機株式会社"},{"key":"制作人","value":"深田祐輔、Kwunchanok、Sornperes"},{"key":"动画制作","value":"RiFF Studio"}],"rating":{"rank":0,"total":12,"count":{"1":0,"2":0,"3":0,"4":1,"5":4,"6":4,"7":3,"8":0,"9":0,"10":0},"score":5.8},"total_episodes":6,"collection":{"on_hold":1,"dropped":7,"wish":11,"collect":14,"doing":3},"id":497924,"eps":6,"meta_tags":["WEB"],"volumes":0,"series":false,"locked":false,"nsfw":false,"type":2}