{"date":"2009-07-06","platform":"TV","images":{"small":"https://lain.bgm.tv/r/200/pic/cover/l/25/e2/1729_i4Psn.jpg","grid":"https://lain.bgm.tv/r/100/pic/cover/l/25/e2/1729_i4Psn.jpg","large":"https://lain.bgm.tv/pic/cover/l/25/e2/1729_i4Psn.jpg","medium":"https://lain.bgm.tv/r/800/pic/cover/l/25/e2/1729_i4Psn.jpg","common":"https://lain.bgm.tv/r/400/pic/cover/l/25/e2/1729_i4Psn.jpg"},"summary":"　　以某高中美术班「GA」的一年级学生当中充满个性的五个女学生为中心，描写她们点缀著各种美术知识的上课情况以及环绕著她们的热闹学校生活。","name":"GA 芸術科アートデザインクラス","name_cn":"GA 艺术科美术设计班","tags":[{"name":"GA","count":184,"total_cont":0},{"name":"艺术科美术设计班","count":142,"total_cont":0},{"name":"治愈系","count":135,"total_cont":0},{"name":"萌","count":119,"total_cont":0},{"name":"TV","count":116,"total_cont":0},{"name":"AIC","count":100,"total_cont":0},{"name":"四格漫改编","count":84,"total_cont":0},{"name":"2009年7月","count":83,"total_cont":0},{"name":"2009","count":78,"total_cont":0},{"name":"芳文社","count":66,"total_cont":0},{"name":"漫画改","count":57,"total_cont":0},{"name":"治愈","count":57,"total_cont":0},{"name":"素描","count":52,"total_cont":0},{"name":"日常","count":49,"total_cont":0},{"name":"户松遥","count":48,"total_cont":0},{"name":"素猫","count":36,"total_cont":0},{"name":"漫改","count":29,"total_cont":0},{"name":"燃與萌的青春","count":27,"total_cont":0},{"name":"芸術科アートデザインクラス","count":24,"total_cont":0},{"name":"四格","count":24,"total_cont":0},{"name":"教授","count":19,"total_cont":0},{"name":"校园","count":18,"total_cont":0},{"name":"百合","count":17,"total_cont":0},{"name":"公主","count":15,"total_cont":0},{"name":"2009年7月番","count":14,"total_cont":0},{"name":"有技术","count":13,"total_cont":0},{"name":"搞笑","count":12,"total_cont":0},{"name":"樱井弘明","count":10,"total_cont":0},{"name":"日本","count":8,"total_cont":0},{"name":"美术","count":7,"total_cont":0}],"infobox":[{"key":"中文名","value":"GA 艺术科美术设计班"},{"key":"话数","value":"12"},{"key":"放送开始","value":"2009年7月6日"},{"key":"放送星期","value":"星期一"},{"key":"官方网站","value":"http://mv.avex.jp/ga/index.html"},{"key":"播放电视台","value":"日本テレビ"},{"key":"播放结束","value":"2009年9月21日"},{"key":"导演","value":"桜井弘明"},{"key":"音乐","value":"ダブルオーツ（安部純、武藤星児）"},{"key":"Copyright","value":"©️きゆづきさとこ・芳文社/GA製作委員会"},{"key":"原作","value":"きゆづきさとこ"},{"key":"系列构成","value":"待田堂子"},{"key":"人物设定","value":"渡辺敦子"},{"key":"企画","value":"高谷与志人、孝壽尚志、松本慶明、大熊保幸、三浦亨、金子一志"},{"key":"制片人","value":"龍貴大、小林宏之、丸山創、斎藤朋之、黄樹弐悠、相田武一郎"},{"key":"製作","value":"GA製作委員会（avex entertainment、芳文社、マーベラス、読売テレビ、AIC、ポニーキャニオン）"},{"key":"动画制片人","value":"先川幸矢"},{"key":"协作制片人","value":"後藤政則、米倉功人"},{"key":"录音","value":"はたしょう二；录音工作室：ドンファンスタジオ"},{"key":"录音助理","value":"藤田直美"},{"key":"音响","value":"ダックスプロダクション；音响制作担当：稲葉順一"},{"key":"音效","value":"川田清貴"},{"key":"宣传","value":"齋藤雅哉"},{"key":"设定制作","value":"岡篤志"},{"key":"制作进行","value":"福田尚哉、持丸健、中野慎也、宮城夢乃、松本博子、松尾進太郎、鈴木良兵、坂本和義、峰海彦、川越崇弘"},{"key":"特效","value":"長谷川敏生"},{"key":"色彩指定","value":"漆戸幸子、岡田絵美子、片山靖子、月館順子、大武恭子、駒田法子、小野田美香、古川篤史"}],"rating":{"rank":1811,"total":866,"count":{"1":1,"2":1,"3":5,"4":7,"5":41,"6":161,"7":317,"8":235,"9":61,"10":37},"score":7.2},"total_episodes":12,"collection":{"on_hold":152,"dropped":85,"wish":859,"collect":1258,"doing":120},"id":1729,"eps":12,"meta_tags":["TV","日本","漫画改"],"volumes":0,"series":false,"locked":false,"nsfw":false,"type":2}